[{"name":"哈囉","checkInStatus":[true,true,true,true,true,true,true],"weeklyAttendence":false},{"name":"B","checkInStatus":[false,false,false,false,true,true,false],"weeklyAttendence":false},{"name":"AA","checkInStatus":[false,false,false,false,true,true,false],"weeklyAttendence":false},{"name":"C","checkInStatus":[false,false,false,false,false,true,false],"weeklyAttendence":false},{"name":"CC","checkInStatus":[false,false,false,false,false,true,false],"weeklyAttendence":false},{"name":"CCC","checkInStatus":[false,false,false,false,false,true,false],"weeklyAttendence":false}]